sun_path_diagrams/__init__.py
sun_path_diagrams/__main__.py
sun_path_diagrams/algorithms_spa.py
sun_path_diagrams/charting.py
sun_path_diagrams/config.py
sun_path_diagrams/gui.py
sun_path_diagrams/tables.py
sun_path_diagrams-1.0.0.dist-info/LICENSE.txt
sun_path_diagrams-1.0.0.dist-info/METADATA
sun_path_diagrams-1.0.0.dist-info/WHEEL
sun_path_diagrams-1.0.0.dist-info/entry_points.txt
sun_path_diagrams-1.0.0.dist-info/top_level.txt
sun_path_diagrams-1.0.0.dist-info/RECORD
