Metadata-Version: 2.1
Name: sun-path-diagrams
Version: 1.0.0
Summary: Plots the horizontal and vertical sun path diagrams
Author-email: Leo Guzman <kuma@mailfence.com>
Maintainer-email: Leo Guzman <kuma@mailfence.com>
License: GNU GENERAL PUBLIC LICENSE
Project-URL: Homepage, https://github.com/kuma-gzt/sun_position
Project-URL: Repository, https://github.com/kuma-gzt/sun_position
Keywords: sun path,sun position,sun diagram,sun chart
Classifier: Development Status :: 5 - Production/Stable
Classifier: Programming Language :: Python
Classifier: Intended Audience :: End Users/Desktop
Classifier: Topic :: Scientific/Engineering :: Visualization
Requires-Python: >=3.9
License-File: LICENSE.txt
Requires-Dist: matplotlib >=3.7
